{
  "league_id": "1264304480178950144",
  "league_name": "Dynasty League",
  "season": "2025",
  "current_week": 15,
  "generated_at": "2025-12-13T01:50:56.176824",
  "teams": [
    {
      "roster_id": 7,
      "owner_id": "992545813546979328",
      "owner_name": "emiliosolay",
      "total_points_scored": 2177.98,
      "total_points_against": 1670.3,
      "total_optimal_points": 2177.98,
      "wins": 12,
      "losses": 2,
      "ties": 0,
      "weeks_played": 14,
      "weekly_scores": [
        {
          "week": 1,
          "points": 153.78,
          "optimal": 153.78,
          "bench": 118.02000000000001,
          "margin": 59.64,
          "opponent_points": 131.3,
          "waiver_moves": 2,
          "faab_spent": 18,
          "has_matchup": true,
          "missed": 0
        },
        {
          "week": 2,
          "points": 174.4,
          "optimal": 174.4,
          "bench": 127.6,
          "margin": 98.04,
          "opponent_points": 76.36,
          "waiver_moves": 0,
          "faab_spent": 0,
          "has_matchup": true,
          "missed": 0
        },
        {
          "week": 3,
          "points": 163.38,
          "optimal": 163.38,
          "bench": 118.3,
          "margin": 83.92,
          "opponent_points": 103.34,
          "waiver_moves": 0,
          "faab_spent": 0,
          "has_matchup": true,
          "missed": 0
        },
        {
          "week": 4,
          "points": 186.58,
          "optimal": 186.58,
          "bench": 87.53999999999998,
          "margin": 66.64000000000001,
          "opponent_points": 129.74,
          "waiver_moves": 0,
          "faab_spent": 0,
          "has_matchup": true,
          "missed": 0
        },
        {
          "week": 5,
          "points": 153.6,
          "optimal": 153.6,
          "bench": 64.2,
          "margin": 59.94,
          "opponent_points": 130.38,
          "waiver_moves": 1,
          "faab_spent": 3,
          "has_matchup": true,
          "missed": 0
        },
        {
          "week": 6,
          "points": 145.9,
          "optimal": 145.9,
          "bench": 103.26,
          "margin": 66.94000000000001,
          "opponent_points": 122.1,
          "waiver_moves": 0,
          "faab_spent": 0,
          "has_matchup": true,
          "missed": 0
        },
        {
          "week": 7,
          "points": 200.76,
          "optimal": 200.76,
          "bench": 85.08,
          "margin": 94.19999999999999,
          "opponent_points": 129.06,
          "waiver_moves": 0,
          "faab_spent": 0,
          "has_matchup": true,
          "missed": 0
        },
        {
          "week": 8,
          "points": 133.82,
          "optimal": 133.82,
          "bench": 39.900000000000006,
          "margin": 35.099999999999994,
          "opponent_points": 115.34,
          "waiver_moves": 0,
          "faab_spent": 0,
          "has_matchup": true,
          "missed": 0
        },
        {
          "week": 9,
          "points": 197.96,
          "optimal": 197.96,
          "bench": 110.8,
          "margin": 88.94000000000001,
          "opponent_points": 126.56,
          "waiver_moves": 0,
          "faab_spent": 0,
          "has_matchup": true,
          "missed": 0
        },
        {
          "week": 10,
          "points": 186.54,
          "optimal": 186.54,
          "bench": 55.8,
          "margin": 97.11999999999999,
          "opponent_points": 162.08,
          "waiver_moves": 0,
          "faab_spent": 0,
          "has_matchup": true,
          "missed": 0
        },
        {
          "week": 11,
          "points": 108.72,
          "optimal": 108.72,
          "bench": 34.660000000000004,
          "margin": 23.120000000000005,
          "opponent_points": 85.6,
          "waiver_moves": 1,
          "faab_spent": 10,
          "has_matchup": true,
          "missed": 0
        },
        {
          "week": 12,
          "points": 145.44,
          "optimal": 145.44,
          "bench": 52.059999999999995,
          "margin": 48.7,
          "opponent_points": 119.1,
          "waiver_moves": 0,
          "faab_spent": 0,
          "has_matchup": true,
          "missed": 0
        },
        {
          "week": 13,
          "points": 109.54,
          "optimal": 109.54,
          "bench": 79.14,
          "margin": 7.1200000000000045,
          "opponent_points": 115.12,
          "waiver_moves": 1,
          "faab_spent": 3,
          "has_matchup": true,
          "missed": 0
        },
        {
          "week": 14,
          "points": 117.56,
          "optimal": 117.56,
          "bench": 50.0,
          "margin": 61.78,
          "opponent_points": 124.22,
          "waiver_moves": 1,
          "faab_spent": 10,
          "has_matchup": true,
          "missed": 0
        }
      ],
      "points_left_on_bench": 0,
      "total_bench_points": 1126.36,
      "faab_spent": 44,
      "waiver_moves": 6,
      "safety_margin_sum": 891.2,
      "close_calls": 1,
      "eliminated_week": null,
      "all_play_wins": 95,
      "all_play_losses": 31,
      "all_play_ties": 0,
      "average_points": 155.57,
      "avg_points_per_game": 155.57,
      "efficiency_rate": 100.0,
      "faab_efficiency": 0,
      "points_per_faab": 49.499545454545455,
      "pythagorean_wins": 9.273895602757422,
      "luck_factor": 2.726104397242578,
      "trend": -20.177412097448087,
      "avg_margin_above_last": 0,
      "avg_safety_margin": 0,
      "consistency_score": 4.995033641515189
    },
    {
      "roster_id": 5,
      "owner_id": "867509897846259712",
      "owner_name": "BTThomp",
      "total_points_scored": 1938.8799999999999,
      "total_points_against": 1892.76,
      "total_optimal_points": 1938.8799999999999,
      "wins": 6,
      "losses": 8,
      "ties": 0,
      "weeks_played": 14,
      "weekly_scores": [
        {
          "week": 1,
          "points": 131.3,
          "optimal": 131.3,
          "bench": 106.78,
          "margin": 37.16000000000001,
          "opponent_points": 153.78,
          "waiver_moves": 0,
          "faab_spent": 0,
          "has_matchup": true,
          "missed": 0
        },
        {
          "week": 2,
          "points": 176.8,
          "optimal": 176.8,
          "bench": 84.52000000000001,
          "margin": 100.44000000000001,
          "opponent_points": 135.1,
          "waiver_moves": 0,
          "faab_spent": 0,
          "has_matchup": true,
          "missed": 0
        },
        {
          "week": 3,
          "points": 152.34,
          "optimal": 152.34,
          "bench": 97.46,
          "margin": 72.88000000000001,
          "opponent_points": 132.82,
          "waiver_moves": 1,
          "faab_spent": 1,
          "has_matchup": true,
          "missed": 0
        },
        {
          "week": 4,
          "points": 143.36,
          "optimal": 143.36,
          "bench": 123.41999999999999,
          "margin": 23.420000000000016,
          "opponent_points": 121.16,
          "waiver_moves": 1,
          "faab_spent": 10,
          "has_matchup": true,
          "missed": 0
        },
        {
          "week": 5,
          "points": 123.12,
          "optimal": 123.12,
          "bench": 103.69999999999999,
          "margin": 29.460000000000008,
          "opponent_points": 93.66,
          "waiver_moves": 0,
          "faab_spent": 0,
          "has_matchup": true,
          "missed": 0
        },
        {
          "week": 6,
          "points": 128.82,
          "optimal": 128.82,
          "bench": 130.14000000000001,
          "margin": 49.86,
          "opponent_points": 148.78,
          "waiver_moves": 0,
          "faab_spent": 0,
          "has_matchup": true,
          "missed": 0
        },
        {
          "week": 7,
          "points": 140.46,
          "optimal": 140.46,
          "bench": 73.78,
          "margin": 33.900000000000006,
          "opponent_points": 149.52,
          "waiver_moves": 0,
          "faab_spent": 0,
          "has_matchup": true,
          "missed": 0
        },
        {
          "week": 8,
          "points": 169.6,
          "optimal": 169.6,
          "bench": 60.800000000000004,
          "margin": 70.88,
          "opponent_points": 98.72,
          "waiver_moves": 0,
          "faab_spent": 0,
          "has_matchup": true,
          "missed": 0
        },
        {
          "week": 9,
          "points": 115.42,
          "optimal": 115.42,
          "bench": 139.78,
          "margin": 6.400000000000006,
          "opponent_points": 121.68,
          "waiver_moves": 0,
          "faab_spent": 0,
          "has_matchup": true,
          "missed": 0
        },
        {
          "week": 10,
          "points": 162.08,
          "optimal": 162.08,
          "bench": 72.72,
          "margin": 72.66000000000001,
          "opponent_points": 186.54,
          "waiver_moves": 0,
          "faab_spent": 0,
          "has_matchup": true,
          "missed": 0
        },
        {
          "week": 11,
          "points": 132.44,
          "optimal": 132.44,
          "bench": 103.6,
          "margin": 46.84,
          "opponent_points": 157.92,
          "waiver_moves": 0,
          "faab_spent": 0,
          "has_matchup": true,
          "missed": 0
        },
        {
          "week": 12,
          "points": 147.2,
          "optimal": 147.2,
          "bench": 88.7,
          "margin": 50.459999999999994,
          "opponent_points": 129.88,
          "waiver_moves": 0,
          "faab_spent": 0,
          "has_matchup": true,
          "missed": 0
        },
        {
          "week": 13,
          "points": 123.1,
          "optimal": 123.1,
          "bench": 90.36000000000001,
          "margin": 20.679999999999993,
          "opponent_points": 125.7,
          "waiver_moves": 0,
          "faab_spent": 0,
          "has_matchup": true,
          "missed": 0
        },
        {
          "week": 14,
          "points": 92.84,
          "optimal": 92.84,
          "bench": 67.46,
          "margin": 37.06,
          "opponent_points": 137.5,
          "waiver_moves": 0,
          "faab_spent": 0,
          "has_matchup": true,
          "missed": 0
        }
      ],
      "points_left_on_bench": 0,
      "total_bench_points": 1343.2199999999998,
      "faab_spent": 11,
      "waiver_moves": 2,
      "safety_margin_sum": 652.0999999999999,
      "close_calls": 1,
      "eliminated_week": null,
      "all_play_wins": 82,
      "all_play_losses": 44,
      "all_play_ties": 0,
      "average_points": 138.49142857142857,
      "avg_points_per_game": 138.49142857142857,
      "efficiency_rate": 100.0,
      "faab_efficiency": 0,
      "points_per_faab": 176.26181818181817,
      "pythagorean_wins": 7.213954800478579,
      "luck_factor": -1.2139548004785787,
      "trend": -12.59627551301095,
      "avg_margin_above_last": 0,
      "avg_safety_margin": 0,
      "consistency_score": 6.165932703901437
    },
    {
      "roster_id": 4,
      "owner_id": "992533962855608320",
      "owner_name": "SeanRabenaldt",
      "total_points_scored": 1927.88,
      "total_points_against": 1890.5000000000002,
      "total_optimal_points": 1927.88,
      "wins": 8,
      "losses": 6,
      "ties": 0,
      "weeks_played": 14,
      "weekly_scores": [
        {
          "week": 1,
          "points": 128.28,
          "optimal": 128.28,
          "bench": 81.2,
          "margin": 34.14,
          "opponent_points": 119.56,
          "waiver_moves": 0,
          "faab_spent": 0,
          "has_matchup": true,
          "missed": 0
        },
        {
          "week": 2,
          "points": 135.1,
          "optimal": 135.1,
          "bench": 84.3,
          "margin": 58.739999999999995,
          "opponent_points": 176.8,
          "waiver_moves": 0,
          "faab_spent": 0,
          "has_matchup": true,
          "missed": 0
        },
        {
          "week": 3,
          "points": 131.48,
          "optimal": 131.48,
          "bench": 103.4,
          "margin": 52.019999999999996,
          "opponent_points": 127.68,
          "waiver_moves": 0,
          "faab_spent": 0,
          "has_matchup": true,
          "missed": 0
        },
        {
          "week": 4,
          "points": 133.98,
          "optimal": 133.98,
          "bench": 63.3,
          "margin": 14.039999999999992,
          "opponent_points": 119.94,
          "waiver_moves": 2,
          "faab_spent": 17,
          "has_matchup": true,
          "missed": 0
        },
        {
          "week": 5,
          "points": 187.58,
          "optimal": 187.58,
          "bench": 36.919999999999995,
          "margin": 93.92000000000002,
          "opponent_points": 158.52,
          "waiver_moves": 0,
          "faab_spent": 0,
          "has_matchup": true,
          "missed": 0
        },
        {
          "week": 6,
          "points": 118.9,
          "optimal": 118.9,
          "bench": 42.2,
          "margin": 39.94000000000001,
          "opponent_points": 148.02,
          "waiver_moves": 1,
          "faab_spent": 1,
          "has_matchup": true,
          "missed": 0
        },
        {
          "week": 7,
          "points": 129.06,
          "optimal": 129.06,
          "bench": 45.800000000000004,
          "margin": 22.5,
          "opponent_points": 200.76,
          "waiver_moves": 1,
          "faab_spent": 4,
          "has_matchup": true,
          "missed": 0
        },
        {
          "week": 8,
          "points": 108.64,
          "optimal": 108.64,
          "bench": 27.7,
          "margin": 9.920000000000002,
          "opponent_points": 136.12,
          "waiver_moves": 1,
          "faab_spent": 1,
          "has_matchup": true,
          "missed": 0
        },
        {
          "week": 9,
          "points": 124.38,
          "optimal": 124.38,
          "bench": 138.5,
          "margin": 15.36,
          "opponent_points": 132.76,
          "waiver_moves": 0,
          "faab_spent": 0,
          "has_matchup": true,
          "missed": 0
        },
        {
          "week": 10,
          "points": 155.34,
          "optimal": 155.34,
          "bench": 102.4,
          "margin": 65.92,
          "opponent_points": 132.36,
          "waiver_moves": 1,
          "faab_spent": 6,
          "has_matchup": true,
          "missed": 0
        },
        {
          "week": 11,
          "points": 157.92,
          "optimal": 157.92,
          "bench": 32.199999999999996,
          "margin": 72.32,
          "opponent_points": 132.44,
          "waiver_moves": 0,
          "faab_spent": 0,
          "has_matchup": true,
          "missed": 0
        },
        {
          "week": 12,
          "points": 130.3,
          "optimal": 130.3,
          "bench": 70.1,
          "margin": 33.56000000000002,
          "opponent_points": 144.88,
          "waiver_moves": 0,
          "faab_spent": 0,
          "has_matchup": true,
          "missed": 0
        },
        {
          "week": 13,
          "points": 117.66,
          "optimal": 117.66,
          "bench": 89.57999999999998,
          "margin": 15.239999999999995,
          "opponent_points": 104.88,
          "waiver_moves": 0,
          "faab_spent": 0,
          "has_matchup": true,
          "missed": 0
        },
        {
          "week": 14,
          "points": 169.26,
          "optimal": 169.26,
          "bench": 80.08,
          "margin": 113.47999999999999,
          "opponent_points": 55.78,
          "waiver_moves": 1,
          "faab_spent": 67,
          "has_matchup": true,
          "missed": 0
        }
      ],
      "points_left_on_bench": 0,
      "total_bench_points": 997.68,
      "faab_spent": 96,
      "waiver_moves": 7,
      "safety_margin_sum": 641.1000000000001,
      "close_calls": 1,
      "eliminated_week": null,
      "all_play_wins": 72,
      "all_play_losses": 54,
      "all_play_ties": 0,
      "average_points": 137.7057142857143,
      "avg_points_per_game": 137.7057142857143,
      "efficiency_rate": 100.0,
      "faab_efficiency": 0,
      "points_per_faab": 20.082083333333333,
      "pythagorean_wins": 7.174026859332791,
      "luck_factor": 0.8259731406672088,
      "trend": 0.9931461847556288,
      "avg_margin_above_last": 0,
      "avg_safety_margin": 0,
      "consistency_score": 6.276107672901538
    },
    {
      "roster_id": 6,
      "owner_id": "466651430967570432",
      "owner_name": "Sangha",
      "total_points_scored": 1762.4800000000002,
      "total_points_against": 1813.2600000000002,
      "total_optimal_points": 1762.4800000000002,
      "wins": 7,
      "losses": 7,
      "ties": 0,
      "weeks_played": 14,
      "weekly_scores": [
        {
          "week": 1,
          "points": 94.84,
          "optimal": 94.84,
          "bench": 99.4,
          "margin": 0.7000000000000028,
          "opponent_points": 131.68,
          "waiver_moves": 0,
          "faab_spent": 0,
          "has_matchup": true,
          "missed": 0
        },
        {
          "week": 2,
          "points": 125.32,
          "optimal": 125.32,
          "bench": 123.16,
          "margin": 48.959999999999994,
          "opponent_points": 145.48,
          "waiver_moves": 1,
          "faab_spent": 2,
          "has_matchup": true,
          "missed": 0
        },
        {
          "week": 3,
          "points": 79.46,
          "optimal": 79.46,
          "bench": 104.28,
          "margin": 0.0,
          "opponent_points": 91.44,
          "waiver_moves": 2,
          "faab_spent": 3,
          "has_matchup": true,
          "missed": 0
        },
        {
          "week": 4,
          "points": 173.04,
          "optimal": 173.04,
          "bench": 64.46,
          "margin": 53.099999999999994,
          "opponent_points": 148.42,
          "waiver_moves": 1,
          "faab_spent": 4,
          "has_matchup": true,
          "missed": 0
        },
        {
          "week": 5,
          "points": 148.38,
          "optimal": 148.38,
          "bench": 58.89999999999999,
          "margin": 54.72,
          "opponent_points": 147.28,
          "waiver_moves": 0,
          "faab_spent": 0,
          "has_matchup": true,
          "missed": 0
        },
        {
          "week": 6,
          "points": 122.1,
          "optimal": 122.1,
          "bench": 59.540000000000006,
          "margin": 43.14,
          "opponent_points": 145.9,
          "waiver_moves": 0,
          "faab_spent": 0,
          "has_matchup": true,
          "missed": 0
        },
        {
          "week": 7,
          "points": 149.52,
          "optimal": 149.52,
          "bench": 75.64,
          "margin": 42.96000000000001,
          "opponent_points": 140.46,
          "waiver_moves": 0,
          "faab_spent": 0,
          "has_matchup": true,
          "missed": 0
        },
        {
          "week": 8,
          "points": 136.12,
          "optimal": 136.12,
          "bench": 66.04,
          "margin": 37.400000000000006,
          "opponent_points": 108.64,
          "waiver_moves": 0,
          "faab_spent": 0,
          "has_matchup": true,
          "missed": 0
        },
        {
          "week": 9,
          "points": 109.02,
          "optimal": 109.02,
          "bench": 45.49999999999999,
          "margin": 0.0,
          "opponent_points": 126.62,
          "waiver_moves": 0,
          "faab_spent": 0,
          "has_matchup": true,
          "missed": 0
        },
        {
          "week": 10,
          "points": 97.12,
          "optimal": 97.12,
          "bench": 39.9,
          "margin": 7.700000000000003,
          "opponent_points": 145.72,
          "waiver_moves": 0,
          "faab_spent": 0,
          "has_matchup": true,
          "missed": 0
        },
        {
          "week": 11,
          "points": 138.88,
          "optimal": 138.88,
          "bench": 63.12,
          "margin": 53.28,
          "opponent_points": 117.58,
          "waiver_moves": 2,
          "faab_spent": 13,
          "has_matchup": true,
          "missed": 0
        },
        {
          "week": 12,
          "points": 118.72,
          "optimal": 118.72,
          "bench": 37.4,
          "margin": 21.980000000000004,
          "opponent_points": 96.74,
          "waiver_moves": 0,
          "faab_spent": 0,
          "has_matchup": true,
          "missed": 0
        },
        {
          "week": 13,
          "points": 146.96,
          "optimal": 146.96,
          "bench": 110.2,
          "margin": 44.540000000000006,
          "opponent_points": 149.86,
          "waiver_moves": 0,
          "faab_spent": 0,
          "has_matchup": true,
          "missed": 0
        },
        {
          "week": 14,
          "points": 123.0,
          "optimal": 123.0,
          "bench": 62.6,
          "margin": 67.22,
          "opponent_points": 117.44,
          "waiver_moves": 0,
          "faab_spent": 0,
          "has_matchup": true,
          "missed": 0
        }
      ],
      "points_left_on_bench": 0,
      "total_bench_points": 1010.14,
      "faab_spent": 22,
      "waiver_moves": 6,
      "safety_margin_sum": 475.70000000000005,
      "close_calls": 2,
      "eliminated_week": null,
      "all_play_wins": 60,
      "all_play_losses": 66,
      "all_play_ties": 0,
      "average_points": 125.89142857142859,
      "avg_points_per_game": 125.89142857142859,
      "efficiency_rate": 100.0,
      "faab_efficiency": 0,
      "points_per_faab": 80.11272727272728,
      "pythagorean_wins": 6.747594163906081,
      "luck_factor": 0.252405836093919,
      "trend": 2.914075620716249,
      "avg_margin_above_last": 0,
      "avg_safety_margin": 0,
      "consistency_score": 4.978916086041576
    },
    {
      "roster_id": 2,
      "owner_id": "865700190626136064",
      "owner_name": "NLadocsi",
      "total_points_scored": 1741.9,
      "total_points_against": 1700.8999999999999,
      "total_optimal_points": 1741.9,
      "wins": 9,
      "losses": 5,
      "ties": 0,
      "weeks_played": 14,
      "weekly_scores": [
        {
          "week": 1,
          "points": 110.2,
          "optimal": 110.2,
          "bench": 61.96000000000001,
          "margin": 16.060000000000002,
          "opponent_points": 94.14,
          "waiver_moves": 0,
          "faab_spent": 0,
          "has_matchup": true,
          "missed": 0
        },
        {
          "week": 2,
          "points": 145.48,
          "optimal": 145.48,
          "bench": 97.18,
          "margin": 69.11999999999999,
          "opponent_points": 125.32,
          "waiver_moves": 0,
          "faab_spent": 0,
          "has_matchup": true,
          "missed": 0
        },
        {
          "week": 3,
          "points": 113.92,
          "optimal": 113.92,
          "bench": 119.73999999999998,
          "margin": 34.46000000000001,
          "opponent_points": 110.94,
          "waiver_moves": 0,
          "faab_spent": 0,
          "has_matchup": true,
          "missed": 0
        },
        {
          "week": 4,
          "points": 129.74,
          "optimal": 129.74,
          "bench": 92.60000000000001,
          "margin": 9.800000000000011,
          "opponent_points": 186.58,
          "waiver_moves": 1,
          "faab_spent": 10,
          "has_matchup": true,
          "missed": 0
        },
        {
          "week": 5,
          "points": 93.66,
          "optimal": 93.66,
          "bench": 113.32,
          "margin": 0.0,
          "opponent_points": 123.12,
          "waiver_moves": 0,
          "faab_spent": 0,
          "has_matchup": true,
          "missed": 0
        },
        {
          "week": 6,
          "points": 146.3,
          "optimal": 146.3,
          "bench": 63.46000000000001,
          "margin": 67.34000000000002,
          "opponent_points": 78.96,
          "waiver_moves": 1,
          "faab_spent": 20,
          "has_matchup": true,
          "missed": 0
        },
        {
          "week": 7,
          "points": 134.08,
          "optimal": 134.08,
          "bench": 70.82000000000001,
          "margin": 27.52000000000001,
          "opponent_points": 131.02,
          "waiver_moves": 1,
          "faab_spent": 1,
          "has_matchup": true,
          "missed": 0
        },
        {
          "week": 8,
          "points": 112.56,
          "optimal": 112.56,
          "bench": 86.80000000000001,
          "margin": 13.840000000000003,
          "opponent_points": 140.42,
          "waiver_moves": 1,
          "faab_spent": 5,
          "has_matchup": true,
          "missed": 0
        },
        {
          "week": 9,
          "points": 132.76,
          "optimal": 132.76,
          "bench": 68.98,
          "margin": 23.739999999999995,
          "opponent_points": 124.38,
          "waiver_moves": 1,
          "faab_spent": 3,
          "has_matchup": true,
          "missed": 0
        },
        {
          "week": 10,
          "points": 102.6,
          "optimal": 102.6,
          "bench": 31.759999999999994,
          "margin": 13.179999999999993,
          "opponent_points": 126.66,
          "waiver_moves": 0,
          "faab_spent": 0,
          "has_matchup": true,
          "missed": 0
        },
        {
          "week": 11,
          "points": 117.58,
          "optimal": 117.58,
          "bench": 86.04,
          "margin": 31.980000000000004,
          "opponent_points": 138.88,
          "waiver_moves": 1,
          "faab_spent": 10,
          "has_matchup": true,
          "missed": 0
        },
        {
          "week": 12,
          "points": 150.4,
          "optimal": 150.4,
          "bench": 34.1,
          "margin": 53.66000000000001,
          "opponent_points": 118.1,
          "waiver_moves": 0,
          "faab_spent": 0,
          "has_matchup": true,
          "missed": 0
        },
        {
          "week": 13,
          "points": 115.12,
          "optimal": 115.12,
          "bench": 87.19999999999999,
          "margin": 12.700000000000003,
          "opponent_points": 109.54,
          "waiver_moves": 2,
          "faab_spent": 8,
          "has_matchup": true,
          "missed": 0
        },
        {
          "week": 14,
          "points": 137.5,
          "optimal": 137.5,
          "bench": 42.9,
          "margin": 81.72,
          "opponent_points": 92.84,
          "waiver_moves": 0,
          "faab_spent": 0,
          "has_matchup": true,
          "missed": 0
        }
      ],
      "points_left_on_bench": 0,
      "total_bench_points": 1056.8600000000001,
      "faab_spent": 57,
      "waiver_moves": 8,
      "safety_margin_sum": 455.1200000000001,
      "close_calls": 1,
      "eliminated_week": null,
      "all_play_wins": 63,
      "all_play_losses": 63,
      "all_play_ties": 0,
      "average_points": 124.42142857142858,
      "avg_points_per_game": 124.42142857142858,
      "efficiency_rate": 100.0,
      "faab_efficiency": 0,
      "points_per_faab": 30.55964912280702,
      "pythagorean_wins": 7.211685889561383,
      "luck_factor": 1.788314110438617,
      "trend": 7.971754980194039,
      "avg_margin_above_last": 0,
      "avg_safety_margin": 0,
      "consistency_score": 7.121511242823216
    },
    {
      "roster_id": 10,
      "owner_id": "865705907659632640",
      "owner_name": "Taubitz",
      "total_points_scored": 1741.82,
      "total_points_against": 1890.88,
      "total_optimal_points": 1741.82,
      "wins": 6,
      "losses": 8,
      "ties": 0,
      "weeks_played": 14,
      "weekly_scores": [
        {
          "week": 1,
          "points": 135.9,
          "optimal": 135.9,
          "bench": 68.82,
          "margin": 41.760000000000005,
          "opponent_points": 141.0,
          "waiver_moves": 0,
          "faab_spent": 0,
          "has_matchup": true,
          "missed": 0
        },
        {
          "week": 2,
          "points": 116.08,
          "optimal": 116.08,
          "bench": 87.9,
          "margin": 39.72,
          "opponent_points": 84.62,
          "waiver_moves": 1,
          "faab_spent": 5,
          "has_matchup": true,
          "missed": 0
        },
        {
          "week": 3,
          "points": 103.34,
          "optimal": 103.34,
          "bench": 78.20000000000002,
          "margin": 23.88000000000001,
          "opponent_points": 163.38,
          "waiver_moves": 1,
          "faab_spent": 5,
          "has_matchup": true,
          "missed": 0
        },
        {
          "week": 4,
          "points": 148.42,
          "optimal": 148.42,
          "bench": 105.46,
          "margin": 28.47999999999999,
          "opponent_points": 173.04,
          "waiver_moves": 0,
          "faab_spent": 0,
          "has_matchup": true,
          "missed": 0
        },
        {
          "week": 5,
          "points": 158.52,
          "optimal": 158.52,
          "bench": 34.6,
          "margin": 64.86000000000001,
          "opponent_points": 187.58,
          "waiver_moves": 0,
          "faab_spent": 0,
          "has_matchup": true,
          "missed": 0
        },
        {
          "week": 6,
          "points": 148.78,
          "optimal": 148.78,
          "bench": 61.9,
          "margin": 69.82000000000001,
          "opponent_points": 128.82,
          "waiver_moves": 0,
          "faab_spent": 0,
          "has_matchup": true,
          "missed": 0
        },
        {
          "week": 7,
          "points": 131.48,
          "optimal": 131.48,
          "bench": 73.2,
          "margin": 24.919999999999987,
          "opponent_points": 106.56,
          "waiver_moves": 0,
          "faab_spent": 0,
          "has_matchup": true,
          "missed": 0
        },
        {
          "week": 8,
          "points": 140.42,
          "optimal": 140.42,
          "bench": 47.53999999999999,
          "margin": 41.69999999999999,
          "opponent_points": 112.56,
          "waiver_moves": 1,
          "faab_spent": 30,
          "has_matchup": true,
          "missed": 0
        },
        {
          "week": 9,
          "points": 112.72,
          "optimal": 112.72,
          "bench": 23.299999999999997,
          "margin": 3.700000000000003,
          "opponent_points": 118.22,
          "waiver_moves": 0,
          "faab_spent": 0,
          "has_matchup": true,
          "missed": 0
        },
        {
          "week": 10,
          "points": 97.58,
          "optimal": 97.58,
          "bench": 30.0,
          "margin": 8.159999999999997,
          "opponent_points": 89.42,
          "waiver_moves": 0,
          "faab_spent": 0,
          "has_matchup": true,
          "missed": 0
        },
        {
          "week": 11,
          "points": 123.84,
          "optimal": 123.84,
          "bench": 74.5,
          "margin": 38.24000000000001,
          "opponent_points": 124.02,
          "waiver_moves": 0,
          "faab_spent": 0,
          "has_matchup": true,
          "missed": 0
        },
        {
          "week": 12,
          "points": 119.1,
          "optimal": 119.1,
          "bench": 52.9,
          "margin": 22.36,
          "opponent_points": 145.44,
          "waiver_moves": 0,
          "faab_spent": 0,
          "has_matchup": true,
          "missed": 0
        },
        {
          "week": 13,
          "points": 149.86,
          "optimal": 149.86,
          "bench": 70.30000000000001,
          "margin": 47.44000000000001,
          "opponent_points": 146.96,
          "waiver_moves": 0,
          "faab_spent": 0,
          "has_matchup": true,
          "missed": 0
        },
        {
          "week": 14,
          "points": 55.78,
          "optimal": 55.78,
          "bench": 73.2,
          "margin": 0.0,
          "opponent_points": 169.26,
          "waiver_moves": 0,
          "faab_spent": 0,
          "has_matchup": true,
          "missed": 0
        }
      ],
      "points_left_on_bench": 0,
      "total_bench_points": 881.8199999999999,
      "faab_spent": 40,
      "waiver_moves": 3,
      "safety_margin_sum": 455.04,
      "close_calls": 2,
      "eliminated_week": null,
      "all_play_wins": 66,
      "all_play_losses": 60,
      "all_play_ties": 0,
      "average_points": 124.41571428571429,
      "avg_points_per_game": 124.41571428571429,
      "efficiency_rate": 100.0,
      "faab_efficiency": 0,
      "points_per_faab": 43.5455,
      "pythagorean_wins": 6.272660855284272,
      "luck_factor": -0.272660855284272,
      "trend": -12.995985042465161,
      "avg_margin_above_last": 0,
      "avg_safety_margin": 0,
      "consistency_score": 4.595560113402768
    },
    {
      "roster_id": 3,
      "owner_id": "867508658106421248",
      "owner_name": "B-Ray",
      "total_points_scored": 1690.4399999999998,
      "total_points_against": 1759.58,
      "total_optimal_points": 1690.4399999999998,
      "wins": 6,
      "losses": 8,
      "ties": 0,
      "weeks_played": 14,
      "weekly_scores": [
        {
          "week": 1,
          "points": 131.68,
          "optimal": 131.68,
          "bench": 87.16,
          "margin": 37.540000000000006,
          "opponent_points": 94.84,
          "waiver_moves": 0,
          "faab_spent": 0,
          "has_matchup": true,
          "missed": 0
        },
        {
          "week": 2,
          "points": 131.66,
          "optimal": 131.66,
          "bench": 106.18,
          "margin": 55.3,
          "opponent_points": 103.88,
          "waiver_moves": 0,
          "faab_spent": 0,
          "has_matchup": true,
          "missed": 0
        },
        {
          "week": 3,
          "points": 110.94,
          "optimal": 110.94,
          "bench": 76.5,
          "margin": 31.480000000000004,
          "opponent_points": 113.92,
          "waiver_moves": 0,
          "faab_spent": 0,
          "has_matchup": true,
          "missed": 0
        },
        {
          "week": 4,
          "points": 119.94,
          "optimal": 119.94,
          "bench": 71.96,
          "margin": 0.0,
          "opponent_points": 133.98,
          "waiver_moves": 0,
          "faab_spent": 0,
          "has_matchup": true,
          "missed": 0
        },
        {
          "week": 5,
          "points": 137.38,
          "optimal": 137.38,
          "bench": 103.63999999999999,
          "margin": 43.72,
          "opponent_points": 166.4,
          "waiver_moves": 2,
          "faab_spent": 14,
          "has_matchup": true,
          "missed": 0
        },
        {
          "week": 6,
          "points": 107.64,
          "optimal": 107.64,
          "bench": 119.19999999999999,
          "margin": 28.680000000000007,
          "opponent_points": 91.56,
          "waiver_moves": 0,
          "faab_spent": 0,
          "has_matchup": true,
          "missed": 0
        },
        {
          "week": 7,
          "points": 106.56,
          "optimal": 106.56,
          "bench": 53.13999999999999,
          "margin": 0.0,
          "opponent_points": 131.48,
          "waiver_moves": 0,
          "faab_spent": 0,
          "has_matchup": true,
          "missed": 0
        },
        {
          "week": 8,
          "points": 98.72,
          "optimal": 98.72,
          "bench": 21.099999999999998,
          "margin": 0.0,
          "opponent_points": 169.6,
          "waiver_moves": 0,
          "faab_spent": 0,
          "has_matchup": true,
          "missed": 0
        },
        {
          "week": 9,
          "points": 126.56,
          "optimal": 126.56,
          "bench": 84.19999999999999,
          "margin": 17.540000000000006,
          "opponent_points": 197.96,
          "waiver_moves": 0,
          "faab_spent": 0,
          "has_matchup": true,
          "missed": 0
        },
        {
          "week": 10,
          "points": 145.72,
          "optimal": 145.72,
          "bench": 77.61999999999999,
          "margin": 56.3,
          "opponent_points": 97.12,
          "waiver_moves": 0,
          "faab_spent": 0,
          "has_matchup": true,
          "missed": 0
        },
        {
          "week": 11,
          "points": 122.92,
          "optimal": 122.92,
          "bench": 48.959999999999994,
          "margin": 37.32000000000001,
          "opponent_points": 103.06,
          "waiver_moves": 1,
          "faab_spent": 6,
          "has_matchup": true,
          "missed": 0
        },
        {
          "week": 12,
          "points": 118.1,
          "optimal": 118.1,
          "bench": 77.46,
          "margin": 21.36,
          "opponent_points": 150.4,
          "waiver_moves": 0,
          "faab_spent": 0,
          "has_matchup": true,
          "missed": 0
        },
        {
          "week": 13,
          "points": 104.88,
          "optimal": 104.88,
          "bench": 74.47999999999999,
          "margin": 2.4599999999999937,
          "opponent_points": 117.66,
          "waiver_moves": 0,
          "faab_spent": 0,
          "has_matchup": true,
          "missed": 0
        },
        {
          "week": 14,
          "points": 127.74,
          "optimal": 127.74,
          "bench": 78.56,
          "margin": 71.96,
          "opponent_points": 87.72,
          "waiver_moves": 0,
          "faab_spent": 0,
          "has_matchup": true,
          "missed": 0
        }
      ],
      "points_left_on_bench": 0,
      "total_bench_points": 1080.16,
      "faab_spent": 20,
      "waiver_moves": 3,
      "safety_margin_sum": 403.66,
      "close_calls": 1,
      "eliminated_week": null,
      "all_play_wins": 44,
      "all_play_losses": 82,
      "all_play_ties": 0,
      "average_points": 120.74571428571427,
      "avg_points_per_game": 120.74571428571427,
      "efficiency_rate": 100.0,
      "faab_efficiency": 0,
      "points_per_faab": 84.52199999999999,
      "pythagorean_wins": 6.643940402223764,
      "luck_factor": -0.6439404022237643,
      "trend": -3.1794483487533824,
      "avg_margin_above_last": 0,
      "avg_safety_margin": 0,
      "consistency_score": 8.813147022699724
    },
    {
      "roster_id": 1,
      "owner_id": "713832511611965440",
      "owner_name": "agrusa17",
      "total_points_scored": 1689.66,
      "total_points_against": 1876.64,
      "total_optimal_points": 1689.66,
      "wins": 4,
      "losses": 10,
      "ties": 0,
      "weeks_played": 14,
      "weekly_scores": [
        {
          "week": 1,
          "points": 119.56,
          "optimal": 119.56,
          "bench": 104.98000000000002,
          "margin": 25.42,
          "opponent_points": 128.28,
          "waiver_moves": 3,
          "faab_spent": 5,
          "has_matchup": true,
          "missed": 0
        },
        {
          "week": 2,
          "points": 84.62,
          "optimal": 84.62,
          "bench": 94.9,
          "margin": 8.260000000000005,
          "opponent_points": 116.08,
          "waiver_moves": 0,
          "faab_spent": 0,
          "has_matchup": true,
          "missed": 0
        },
        {
          "week": 3,
          "points": 132.82,
          "optimal": 132.82,
          "bench": 85.18,
          "margin": 53.36,
          "opponent_points": 152.34,
          "waiver_moves": 0,
          "faab_spent": 0,
          "has_matchup": true,
          "missed": 0
        },
        {
          "week": 4,
          "points": 141.28,
          "optimal": 141.28,
          "bench": 114.92000000000002,
          "margin": 21.340000000000003,
          "opponent_points": 141.98,
          "waiver_moves": 1,
          "faab_spent": 17,
          "has_matchup": true,
          "missed": 0
        },
        {
          "week": 5,
          "points": 166.4,
          "optimal": 166.4,
          "bench": 73.74000000000002,
          "margin": 72.74000000000001,
          "opponent_points": 137.38,
          "waiver_moves": 1,
          "faab_spent": 21,
          "has_matchup": true,
          "missed": 0
        },
        {
          "week": 6,
          "points": 78.96,
          "optimal": 78.96,
          "bench": 42.480000000000004,
          "margin": 0.0,
          "opponent_points": 146.3,
          "waiver_moves": 3,
          "faab_spent": 12,
          "has_matchup": true,
          "missed": 0
        },
        {
          "week": 7,
          "points": 131.6,
          "optimal": 131.6,
          "bench": 86.7,
          "margin": 25.039999999999992,
          "opponent_points": 154.9,
          "waiver_moves": 0,
          "faab_spent": 0,
          "has_matchup": true,
          "missed": 0
        },
        {
          "week": 8,
          "points": 115.34,
          "optimal": 115.34,
          "bench": 105.87999999999998,
          "margin": 16.620000000000005,
          "opponent_points": 133.82,
          "waiver_moves": 1,
          "faab_spent": 6,
          "has_matchup": true,
          "missed": 0
        },
        {
          "week": 9,
          "points": 126.62,
          "optimal": 126.62,
          "bench": 49.900000000000006,
          "margin": 17.60000000000001,
          "opponent_points": 109.02,
          "waiver_moves": 1,
          "faab_spent": 17,
          "has_matchup": true,
          "missed": 0
        },
        {
          "week": 10,
          "points": 132.36,
          "optimal": 132.36,
          "bench": 49.82,
          "margin": 42.94000000000001,
          "opponent_points": 155.34,
          "waiver_moves": 1,
          "faab_spent": 8,
          "has_matchup": true,
          "missed": 0
        },
        {
          "week": 11,
          "points": 124.02,
          "optimal": 124.02,
          "bench": 127.88000000000001,
          "margin": 38.42,
          "opponent_points": 123.84,
          "waiver_moves": 0,
          "faab_spent": 0,
          "has_matchup": true,
          "missed": 0
        },
        {
          "week": 12,
          "points": 129.88,
          "optimal": 129.88,
          "bench": 55.440000000000005,
          "margin": 33.14,
          "opponent_points": 147.2,
          "waiver_moves": 0,
          "faab_spent": 0,
          "has_matchup": true,
          "missed": 0
        },
        {
          "week": 13,
          "points": 118.48,
          "optimal": 118.48,
          "bench": 86.70000000000002,
          "margin": 16.060000000000002,
          "opponent_points": 102.42,
          "waiver_moves": 0,
          "faab_spent": 0,
          "has_matchup": true,
          "missed": 0
        },
        {
          "week": 14,
          "points": 87.72,
          "optimal": 87.72,
          "bench": 95.38000000000002,
          "margin": 31.939999999999998,
          "opponent_points": 127.74,
          "waiver_moves": 1,
          "faab_spent": 11,
          "has_matchup": true,
          "missed": 0
        }
      ],
      "points_left_on_bench": 0,
      "total_bench_points": 1173.9000000000003,
      "faab_spent": 97,
      "waiver_moves": 12,
      "safety_margin_sum": 402.88,
      "close_calls": 1,
      "eliminated_week": null,
      "all_play_wins": 58,
      "all_play_losses": 68,
      "all_play_ties": 0,
      "average_points": 120.69000000000001,
      "avg_points_per_game": 120.69000000000001,
      "efficiency_rate": 100.0,
      "faab_efficiency": 0,
      "points_per_faab": 17.41917525773196,
      "pythagorean_wins": 6.072431485113245,
      "luck_factor": -2.0724314851132446,
      "trend": -7.178169967133445,
      "avg_margin_above_last": 0,
      "avg_safety_margin": 0,
      "consistency_score": 5.124547330496922
    },
    {
      "roster_id": 9,
      "owner_id": "1265686061632208896",
      "owner_name": "dbyrd55",
      "total_points_scored": 1670.88,
      "total_points_against": 1695.9599999999998,
      "total_optimal_points": 1670.88,
      "wins": 8,
      "losses": 6,
      "ties": 0,
      "weeks_played": 14,
      "weekly_scores": [
        {
          "week": 1,
          "points": 94.14,
          "optimal": 94.14,
          "bench": 83.16,
          "margin": 0.0,
          "opponent_points": 110.2,
          "waiver_moves": 0,
          "faab_spent": 0,
          "has_matchup": true,
          "missed": 0
        },
        {
          "week": 2,
          "points": 103.88,
          "optimal": 103.88,
          "bench": 60.42,
          "margin": 27.519999999999996,
          "opponent_points": 131.66,
          "waiver_moves": 1,
          "faab_spent": 20,
          "has_matchup": true,
          "missed": 0
        },
        {
          "week": 3,
          "points": 91.44,
          "optimal": 91.44,
          "bench": 26.9,
          "margin": 11.980000000000004,
          "opponent_points": 79.46,
          "waiver_moves": 1,
          "faab_spent": 1,
          "has_matchup": true,
          "missed": 0
        },
        {
          "week": 4,
          "points": 121.16,
          "optimal": 121.16,
          "bench": 44.3,
          "margin": 1.2199999999999989,
          "opponent_points": 143.36,
          "waiver_moves": 1,
          "faab_spent": 1,
          "has_matchup": true,
          "missed": 0
        },
        {
          "week": 5,
          "points": 130.38,
          "optimal": 130.38,
          "bench": 15.8,
          "margin": 36.72,
          "opponent_points": 153.6,
          "waiver_moves": 0,
          "faab_spent": 0,
          "has_matchup": true,
          "missed": 0
        },
        {
          "week": 6,
          "points": 148.02,
          "optimal": 148.02,
          "bench": 41.8,
          "margin": 69.06000000000002,
          "opponent_points": 118.9,
          "waiver_moves": 0,
          "faab_spent": 0,
          "has_matchup": true,
          "missed": 0
        },
        {
          "week": 7,
          "points": 154.9,
          "optimal": 154.9,
          "bench": 100.3,
          "margin": 48.34,
          "opponent_points": 131.6,
          "waiver_moves": 0,
          "faab_spent": 0,
          "has_matchup": true,
          "missed": 0
        },
        {
          "week": 8,
          "points": 132.36,
          "optimal": 132.36,
          "bench": 56.72,
          "margin": 33.640000000000015,
          "opponent_points": 129.56,
          "waiver_moves": 0,
          "faab_spent": 0,
          "has_matchup": true,
          "missed": 0
        },
        {
          "week": 9,
          "points": 118.22,
          "optimal": 118.22,
          "bench": 34.739999999999995,
          "margin": 9.200000000000003,
          "opponent_points": 112.72,
          "waiver_moves": 0,
          "faab_spent": 0,
          "has_matchup": true,
          "missed": 0
        },
        {
          "week": 10,
          "points": 126.66,
          "optimal": 126.66,
          "bench": 54.17999999999999,
          "margin": 37.239999999999995,
          "opponent_points": 102.6,
          "waiver_moves": 0,
          "faab_spent": 0,
          "has_matchup": true,
          "missed": 0
        },
        {
          "week": 11,
          "points": 103.06,
          "optimal": 103.06,
          "bench": 29.099999999999998,
          "margin": 17.460000000000008,
          "opponent_points": 122.92,
          "waiver_moves": 0,
          "faab_spent": 0,
          "has_matchup": true,
          "missed": 0
        },
        {
          "week": 12,
          "points": 96.74,
          "optimal": 96.74,
          "bench": 30.479999999999997,
          "margin": 0.0,
          "opponent_points": 118.72,
          "waiver_moves": 0,
          "faab_spent": 0,
          "has_matchup": true,
          "missed": 0
        },
        {
          "week": 13,
          "points": 125.7,
          "optimal": 125.7,
          "bench": 62.64,
          "margin": 23.28,
          "opponent_points": 123.1,
          "waiver_moves": 0,
          "faab_spent": 0,
          "has_matchup": true,
          "missed": 0
        },
        {
          "week": 14,
          "points": 124.22,
          "optimal": 124.22,
          "bench": 70.82000000000001,
          "margin": 68.44,
          "opponent_points": 117.56,
          "waiver_moves": 0,
          "faab_spent": 0,
          "has_matchup": true,
          "missed": 0
        }
      ],
      "points_left_on_bench": 0,
      "total_bench_points": 711.36,
      "faab_spent": 22,
      "waiver_moves": 3,
      "safety_margin_sum": 384.09999999999997,
      "close_calls": 2,
      "eliminated_week": null,
      "all_play_wins": 48,
      "all_play_losses": 78,
      "all_play_ties": 0,
      "average_points": 119.34857142857143,
      "avg_points_per_game": 119.34857142857143,
      "efficiency_rate": 100.0,
      "faab_efficiency": 0,
      "points_per_faab": 75.94909090909091,
      "pythagorean_wins": 6.867567974659528,
      "luck_factor": 1.1324320253404716,
      "trend": -3.179961058444261,
      "avg_margin_above_last": 0,
      "avg_safety_margin": 0,
      "consistency_score": 6.129199499230061
    },
    {
      "roster_id": 8,
      "owner_id": "865996913412022272",
      "owner_name": "McInally",
      "total_points_scored": 1647.88,
      "total_points_against": 1799.02,
      "total_optimal_points": 1647.88,
      "wins": 4,
      "losses": 10,
      "ties": 0,
      "weeks_played": 14,
      "weekly_scores": [
        {
          "week": 1,
          "points": 141.0,
          "optimal": 141.0,
          "bench": 59.760000000000005,
          "margin": 46.86,
          "opponent_points": 135.9,
          "waiver_moves": 2,
          "faab_spent": 2,
          "has_matchup": true,
          "missed": 0
        },
        {
          "week": 2,
          "points": 76.36,
          "optimal": 76.36,
          "bench": 105.09999999999998,
          "margin": 0.0,
          "opponent_points": 174.4,
          "waiver_moves": 2,
          "faab_spent": 8,
          "has_matchup": true,
          "missed": 0
        },
        {
          "week": 3,
          "points": 127.68,
          "optimal": 127.68,
          "bench": 79.94000000000001,
          "margin": 48.22000000000001,
          "opponent_points": 131.48,
          "waiver_moves": 0,
          "faab_spent": 0,
          "has_matchup": true,
          "missed": 0
        },
        {
          "week": 4,
          "points": 141.98,
          "optimal": 141.98,
          "bench": 84.6,
          "margin": 22.039999999999992,
          "opponent_points": 141.28,
          "waiver_moves": 0,
          "faab_spent": 0,
          "has_matchup": true,
          "missed": 0
        },
        {
          "week": 5,
          "points": 147.28,
          "optimal": 147.28,
          "bench": 86.14,
          "margin": 53.620000000000005,
          "opponent_points": 148.38,
          "waiver_moves": 0,
          "faab_spent": 0,
          "has_matchup": true,
          "missed": 0
        },
        {
          "week": 6,
          "points": 91.56,
          "optimal": 91.56,
          "bench": 58.80000000000001,
          "margin": 12.600000000000009,
          "opponent_points": 107.64,
          "waiver_moves": 0,
          "faab_spent": 0,
          "has_matchup": true,
          "missed": 0
        },
        {
          "week": 7,
          "points": 131.02,
          "optimal": 131.02,
          "bench": 18.5,
          "margin": 24.460000000000008,
          "opponent_points": 134.08,
          "waiver_moves": 2,
          "faab_spent": 11,
          "has_matchup": true,
          "missed": 0
        },
        {
          "week": 8,
          "points": 129.56,
          "optimal": 129.56,
          "bench": 88.5,
          "margin": 30.840000000000003,
          "opponent_points": 132.36,
          "waiver_moves": 0,
          "faab_spent": 0,
          "has_matchup": true,
          "missed": 0
        },
        {
          "week": 9,
          "points": 121.68,
          "optimal": 121.68,
          "bench": 55.82,
          "margin": 12.66000000000001,
          "opponent_points": 115.42,
          "waiver_moves": 0,
          "faab_spent": 0,
          "has_matchup": true,
          "missed": 0
        },
        {
          "week": 10,
          "points": 89.42,
          "optimal": 89.42,
          "bench": 69.52000000000001,
          "margin": 0.0,
          "opponent_points": 97.58,
          "waiver_moves": 1,
          "faab_spent": 10,
          "has_matchup": true,
          "missed": 0
        },
        {
          "week": 11,
          "points": 85.6,
          "optimal": 85.6,
          "bench": 50.080000000000005,
          "margin": 0.0,
          "opponent_points": 108.72,
          "waiver_moves": 2,
          "faab_spent": 31,
          "has_matchup": true,
          "missed": 0
        },
        {
          "week": 12,
          "points": 144.88,
          "optimal": 144.88,
          "bench": 91.14,
          "margin": 48.14,
          "opponent_points": 130.3,
          "waiver_moves": 0,
          "faab_spent": 0,
          "has_matchup": true,
          "missed": 0
        },
        {
          "week": 13,
          "points": 102.42,
          "optimal": 102.42,
          "bench": 80.26,
          "margin": 0.0,
          "opponent_points": 118.48,
          "waiver_moves": 0,
          "faab_spent": 0,
          "has_matchup": true,
          "missed": 0
        },
        {
          "week": 14,
          "points": 117.44,
          "optimal": 117.44,
          "bench": 119.78,
          "margin": 61.66,
          "opponent_points": 123.0,
          "waiver_moves": 0,
          "faab_spent": 0,
          "has_matchup": true,
          "missed": 0
        }
      ],
      "points_left_on_bench": 0,
      "total_bench_points": 1047.94,
      "faab_spent": 62,
      "waiver_moves": 9,
      "safety_margin_sum": 361.1,
      "close_calls": 0,
      "eliminated_week": null,
      "all_play_wins": 42,
      "all_play_losses": 84,
      "all_play_ties": 0,
      "average_points": 117.7057142857143,
      "avg_points_per_game": 117.7057142857143,
      "efficiency_rate": 100.0,
      "faab_efficiency": 0,
      "points_per_faab": 26.578709677419358,
      "pythagorean_wins": 6.22309440239462,
      "luck_factor": -2.2230944023946204,
      "trend": 3.2915018083840972,
      "avg_margin_above_last": 0,
      "avg_safety_margin": 0,
      "consistency_score": 4.856749144272241
    }
  ],
  "best_theoretical_lineups": [],
  "avg_best_theoretical_lineup": 0
}